{"trial_id": "02", "hyperparameters": {"space": [{"class_name": "Int", "config": {"name": "n_layers", "default": null, "conditions": [], "min_value": 1, "max_value": 2, "step": 1, "sampling": "linear"}}, {"class_name": "Choice", "config": {"name": "units", "default": 32, "conditions": [], "values": [32, 64, 128], "ordered": true}}, {"class_name": "Choice", "config": {"name": "dropout", "default": 0.1, "conditions": [], "values": [0.1, 0.2, 0.3], "ordered": true}}, {"class_name": "Choice", "config": {"name": "rec_dropout", "default": 0.0, "conditions": [], "values": [0.0, 0.1], "ordered": true}}, {"class_name": "Choice", "config": {"name": "lr", "default": 0.0001, "conditions": [], "values": [0.0001, 0.0005, 0.001], "ordered": true}}], "values": {"n_layers": 1, "units": 32, "dropout": 0.3, "rec_dropout": 0.1, "lr": 0.0005}}, "metrics": {"metrics": {"loss": {"direction": "min", "observations": [{"value": [0.07043173164129257], "step": 15}]}, "mae": {"direction": "min", "observations": [{"value": [0.19450081884860992], "step": 15}]}, "val_loss": {"direction": "min", "observations": [{"value": [0.06998297572135925], "step": 15}]}, "val_mae": {"direction": "min", "observations": [{"value": [0.1782253384590149], "step": 15}]}}}, "score": 0.06998297572135925, "best_step": 15, "status": "COMPLETED", "message": null}